az/__init__.py
az/cli.py
az.cli-0.5.dist-info/LICENSE
az.cli-0.5.dist-info/METADATA
az.cli-0.5.dist-info/WHEEL
az.cli-0.5.dist-info/top_level.txt
az.cli-0.5.dist-info/RECORD
