Metadata-Version: 2.1
Name: az.cli
Version: 0.5
Summary: An interface to execute Azure CLI commands using Python
Home-page: https://github.com/MarkWarneke/Az.Cli
Author: Mark Warneke
Author-email: warneke.mark@gmail.com
License: UNKNOWN
Platform: UNKNOWN
Classifier: Development Status :: 4 - Beta
Classifier: Intended Audience :: Developers
Classifier: Intended Audience :: System Administrators
Classifier: Programming Language :: Python
Classifier: Programming Language :: Python :: 3
Classifier: Programming Language :: Python :: 3.7
Classifier: Programming Language :: Python :: 3.8
Classifier: License :: OSI Approved :: MIT License
Requires-Python: >=3.7
Requires-Dist: azure-cli
